<?xml version="1.0" encoding="UTF-8"?>

<brLevelledPara>
  <brPara brDecisionPointUniqueIdent="BRDP-S1-00001" id="brp-0001">
    <brRelatedTo>
      <sourceDocRef>
        <dmRef referredFragment="Para_6.2.5">
          <dmRefIdent>
            <dmCode modelIdentCode="S1000D" systemDiffCode="A" systemCode="01" subSystemCode="0" subSubSystemCode="3" assyCode="0000" disassyCode="00" disassyCodeVariant="A" infoCode="040" infoCodeVariant="A" itemLocationCode="A"/>
          </dmRefIdent>
          <dmRefAddressItems>
            <dmTitle>
              <techName>How to use the specification</techName>
            </dmTitle>
          </dmRefAddressItems>
        </dmRef>
      </sourceDocRef>
      <brCategoryGroup>
        <brCategory brCategoryNumber="Cat002">
          <title>Product definition business rules</title>
          <brCategoryDescription>
            <para>Product definition business rules cover the data module coding strategy related to how the Product is broken down (eg, physical or functional). Included is the definition of the model identification codes to be used in the Product and its subsystems. Supplier subsystems and identifications also need to be considered.</para>
          </brCategoryDescription>
        </brCategory>
      </brCategoryGroup>
      <s1000dSchemas appliccrossreftableXsd="1" brexXsd="1" checklistXsd="1" commentXsd="1" comrepXsd="1" condcrossreftableXsd="1" containerXsd="1" crewXsd="1" ddnXsd="1" descriptXsd="1" dmlXsd="1" faultXsd="1" frontmatterXsd="1" ipdXsd="1" learningXsd="1" pmXsd="1" prdcrossreftableXsd="1" procedXsd="1" processXsd="1" sbXsd="1" schedulXsd="1" scocontentXsd="1" scormcontentpackageXsd="1" updateXsd="1" wrngdataXsd="1" wrngfldsXsd="1" brdocXsd="1" icnmetadataXsd="1"/>
    </brRelatedTo>
    <brDecisionPointContent>
      <title>Use of &#34;I&#34; and &#34;O&#34;:</title>
      <brDecisionPointText>
        <para>Decide whether and when to use the alpha characters &#34;I&#34; and &#34;O&#34;.</para>
      </brDecisionPointText>
      <brDecisionPointValueGroup brDecisionValueSelection="single">
        <brDecisionPointValue brDecisionValueAllowed="Yes">
          <para>In case of Yes, decide in which specific cases the characters &#34;I&#34; and &#34;O&#34; are allowed to be used in codes (like in model identification codes).</para>
        </brDecisionPointValue>
        <brDecisionPointValue brDecisionValueAllowed="No">
          <para>In case of No, consider whether there should be exceptions defined (like the use of the characters of &#34;I&#34; and &#34;O&#34; characters in model identification codes).</para>
        </brDecisionPointValue>
      </brDecisionPointValueGroup>
    </brDecisionPointContent>
    <brDecision>
      <brDecisionPending/>
    </brDecision>
  </brPara>
  <brPara brDecisionPointUniqueIdent="BRDP-S1-00002" id="brp-0002">
    <brRelatedTo>
      <sourceDocRef>
        <dmRef referredFragment="Para_7">
          <dmRefIdent>
            <dmCode modelIdentCode="S1000D" systemDiffCode="A" systemCode="01" subSystemCode="0" subSubSystemCode="3" assyCode="0000" disassyCode="00" disassyCodeVariant="A" infoCode="040" infoCodeVariant="A" itemLocationCode="A"/>
          </dmRefIdent>
          <dmRefAddressItems>
            <dmTitle>
              <techName>How to use the specification</techName>
            </dmTitle>
          </dmRefAddressItems>
        </dmRef>
      </sourceDocRef>
      <brCategoryGroup>
        <brCategory brCategoryNumber="Cat005">
          <title>Business process business rules</title>
          <brCategoryDescription>
            <para>Business process business rules cover how technical publications development is coordinated with other disciplines within an organization or within the project level at that organization or the project as a whole. For example, they describe the rules and relationships with LSA, S2000M compliant initial provisioning, engineering/design and training (eg, SCORM conformance).</para>
          </brCategoryDescription>
        </brCategory>
      </brCategoryGroup>
      <s1000dSchemas appliccrossreftableXsd="1" brexXsd="1" checklistXsd="1" commentXsd="1" comrepXsd="1" condcrossreftableXsd="1" containerXsd="1" crewXsd="1" ddnXsd="1" descriptXsd="1" dmlXsd="1" faultXsd="1" frontmatterXsd="1" ipdXsd="1" learningXsd="1" pmXsd="1" prdcrossreftableXsd="1" procedXsd="1" processXsd="1" sbXsd="1" schedulXsd="1" scocontentXsd="1" scormcontentpackageXsd="1" updateXsd="1" wrngdataXsd="1" wrngfldsXsd="1" brdocXsd="1" icnmetadataXsd="1"/>
    </brRelatedTo>
    <brDecisionPointContent>
      <title>List of permitted CAGE codes and/or names to be used for the technical publication project:</title>
      <brDecisionPointText>
        <para>Create a list of permitted CAGE codes and/or names of the enterprises.</para>
      </brDecisionPointText>
      <brDecisionPointValueGroup brDecisionValueSelection="single">
        <brDecisionPointValue brDecisionValueAllowed="Text">
          <para>A list of sets of five character codes applied to and registered by NSPA.</para>
        </brDecisionPointValue>
      </brDecisionPointValueGroup>
    </brDecisionPointContent>
    <brDecision>
      <brDecisionPending/>
    </brDecision>
  </brPara>
  <brPara brDecisionPointUniqueIdent="BRDP-S1-00003" id="brp-0003">
    <brRelatedTo>
      <sourceDocRef>
        <dmRef referredFragment="Para_2.1.3">
          <dmRefIdent>
            <dmCode modelIdentCode="S1000D" systemDiffCode="A" systemCode="02" subSystemCode="0" subSubSystemCode="5" assyCode="0100" disassyCode="00" disassyCodeVariant="A" infoCode="040" infoCodeVariant="A" itemLocationCode="A"/>
          </dmRefIdent>
          <dmRefAddressItems>
            <dmTitle>
              <techName>Business rules</techName>
              <infoName>Categories and layers</infoName>
            </dmTitle>
          </dmRefAddressItems>
        </dmRef>
      </sourceDocRef>
      <brCategoryGroup>
        <brCategory brCategoryNumber="Cat001">
          <title>General</title>
          <brCategoryDescription>
            <para>General business rules cover all decisions made by a project or an organization that are not covered by any of the specific business rule categories below. They serve as overall decisions for the implementation of S1000D.</para>
          </brCategoryDescription>
        </brCategory>
      </brCategoryGroup>
      <s1000dSchemas appliccrossreftableXsd="1" brexXsd="1" checklistXsd="1" commentXsd="1" comrepXsd="1" condcrossreftableXsd="1" containerXsd="1" crewXsd="1" ddnXsd="1" descriptXsd="1" dmlXsd="1" faultXsd="1" frontmatterXsd="1" ipdXsd="1" learningXsd="1" pmXsd="1" prdcrossreftableXsd="1" procedXsd="1" processXsd="1" sbXsd="1" schedulXsd="1" scocontentXsd="1" scormcontentpackageXsd="1" updateXsd="1" wrngdataXsd="1" wrngfldsXsd="1" brdocXsd="1" icnmetadataXsd="1"/>
    </brRelatedTo>
    <brDecisionPointContent>
      <title>Issue of S1000D to be used:</title>
      <brDecisionPointText>
        <para>Decide which issue or issues of S1000D to be used.</para>
      </brDecisionPointText>
      <brDecisionPointValueGroup brDecisionValueSelection="multiple">
        <brDecisionPointValue brDecisionValueAllowed="S1000D_1-6">
          <para>S1000D Issue 1.6</para>
        </brDecisionPointValue>
        <brDecisionPointValue brDecisionValueAllowed="S1000D_1-7">
          <para>S1000D Issue 1.7</para>
        </brDecisionPointValue>
        <brDecisionPointValue brDecisionValueAllowed="S1000D_1-8">
          <para>S1000D Issue 1.8</para>
        </brDecisionPointValue>
        <brDecisionPointValue brDecisionValueAllowed="S1000D_1-8-1">
          <para>S1000D Issue 1.8.1</para>
        </brDecisionPointValue>
        <brDecisionPointValue brDecisionValueAllowed="S1000D_1-9">
          <para>S1000D Issue 1.9</para>
        </brDecisionPointValue>
        <brDecisionPointValue brDecisionValueAllowed="S1000D_2-0">
          <para>S1000D Issue 2.0</para>
        </brDecisionPointValue>
        <brDecisionPointValue brDecisionValueAllowed="S1000D_2-1">
          <para>S1000D Issue 2.1</para>
        </brDecisionPointValue>
        <brDecisionPointValue brDecisionValueAllowed="S1000D_2-2">
          <para>S1000D Issue 2.2</para>
        </brDecisionPointValue>
        <brDecisionPointValue brDecisionValueAllowed="S1000D_2-2-1">
          <para>S1000D Issue 2.2.1 patch</para>
        </brDecisionPointValue>
        <brDecisionPointValue brDecisionValueAllowed="S1000D_2-3">
          <para>S1000D Issue 2.3</para>
        </brDecisionPointValue>
        <brDecisionPointValue brDecisionValueAllowed="S1000D_2-3-1">
          <para>S1000D Issue 2.3.1 patch</para>
        </brDecisionPointValue>
        <brDecisionPointValue brDecisionValueAllowed="S1000D_3-0">
          <para>S1000D Issue 3.0</para>
        </brDecisionPointValue>
        <brDecisionPointValue brDecisionValueAllowed="S1000D_3-0-1">
          <para>S1000D Issue 3.0.1 patch</para>
        </brDecisionPointValue>
        <brDecisionPointValue brDecisionValueAllowed="S1000D_4-0">
          <para>S1000D Issue 4.0</para>
        </brDecisionPointValue>
        <brDecisionPointValue brDecisionValueAllowed="S1000D_4-0-1">
          <para>S1000D Issue 4.0.1 patch</para>
        </brDecisionPointValue>
        <brDecisionPointValue brDecisionValueAllowed="S1000D_4-0-2">
          <para>S1000D Issue 4.0.2 patch</para>
        </brDecisionPointValue>
        <brDecisionPointValue brDecisionValueAllowed="S1000D_4-1">
          <para>S1000D Issue 4.1</para>
        </brDecisionPointValue>
        <brDecisionPointValue brDecisionValueAllowed="S1000D_4-1-A">
          <para>S1000D Issue 4.1.A patch</para>
        </brDecisionPointValue>
        <brDecisionPointValue brDecisionValueAllowed="S1000D_4-1-B">
          <para>S1000D Issue 4.1.B patch</para>
        </brDecisionPointValue>
        <brDecisionPointValue brDecisionValueAllowed="S1000D_4-1-C">
          <para>S1000D Issue 4.1.C patch</para>
        </brDecisionPointValue>
        <brDecisionPointValue brDecisionValueAllowed="S1000D_4-2">
          <para>S1000D Issue 4.2</para>
        </brDecisionPointValue>
        <brDecisionPointValue brDecisionValueAllowed="S1000D_4-2-A">
          <para>S1000D Issue 4.2.A patch</para>
        </brDecisionPointValue>
        <brDecisionPointValue brDecisionValueAllowed="S1000D_5-0">
          <para>S1000D Issue 5.0</para>
        </brDecisionPointValue>
        <brDecisionPointValue brDecisionValueAllowed="S1000D_5-0-A">
          <para>S1000D Issue 5.0.A patch</para>
        </brDecisionPointValue>
      </brDecisionPointValueGroup>
    </brDecisionPointContent>
    <brDecision>
      <brDecisionPending/>
    </brDecision>
  </brPara>
</brLevelledPara>